odoo8_addon_save_translation_file-8.0.1.0.0.99.dev8-py2.7-nspkg.pth
odoo8_addon_save_translation_file-8.0.1.0.0.99.dev8.dist-info/DESCRIPTION.rst
odoo8_addon_save_translation_file-8.0.1.0.0.99.dev8.dist-info/METADATA
odoo8_addon_save_translation_file-8.0.1.0.0.99.dev8.dist-info/RECORD
odoo8_addon_save_translation_file-8.0.1.0.0.99.dev8.dist-info/WHEEL
odoo8_addon_save_translation_file-8.0.1.0.0.99.dev8.dist-info/metadata.json
odoo8_addon_save_translation_file-8.0.1.0.0.99.dev8.dist-info/namespace_packages.txt
odoo8_addon_save_translation_file-8.0.1.0.0.99.dev8.dist-info/top_level.txt
odoo_addons/save_translation_file/README.rst
odoo_addons/save_translation_file/__init__.py
odoo_addons/save_translation_file/__openerp__.py
odoo_addons/save_translation_file/save_translation_file.py
odoo_addons/save_translation_file/save_translation_file_view.xml
odoo_addons/save_translation_file/i18n/ca.po
odoo_addons/save_translation_file/i18n/de.po
odoo_addons/save_translation_file/i18n/es.po
odoo_addons/save_translation_file/i18n/es_MX.po
odoo_addons/save_translation_file/i18n/fr.po
odoo_addons/save_translation_file/i18n/hr.po
odoo_addons/save_translation_file/i18n/it.po
odoo_addons/save_translation_file/i18n/nl_NL.po
odoo_addons/save_translation_file/i18n/pt_BR.po
odoo_addons/save_translation_file/i18n/save_translation_file.pot
odoo_addons/save_translation_file/i18n/sl.po
odoo_addons/save_translation_file/i18n/tr.po
odoo_addons/save_translation_file/static/description/icon.png
odoo_addons/save_translation_file/tests/__init__.py
odoo_addons/save_translation_file/tests/test_save_translation_file.py
